AUTHORS.txt
CHANGELOG.txt
FAQ.txt
INSTALL.txt
LICENSE.txt
MANIFEST.in
README.txt
THANKS.txt
TODO.txt
setup.cfg
setup.py
Batcher.egg-info/PKG-INFO
Batcher.egg-info/SOURCES.txt
Batcher.egg-info/dependency_links.txt
Batcher.egg-info/entry_points.txt
Batcher.egg-info/not-zip-safe
Batcher.egg-info/top_level.txt
batcher/__init__.py
doc/Makefile
doc/conf.py
doc/index.rst
tests/test_batch.py