Metadata-Version: 1.0
Name: Batcher
Version: 1
Summary: Cut sliceable objects into batches, eg for paging display on a website
Home-page: UNKNOWN
Author: Oliver Cope
Author-email: oliver@redgecko.org
License: BSD
Platform: UNKNOWN
Classifier: Development Status :: 3 - Alpha
Classifier: Environment :: Web Environment
Classifier: License :: OSI Approved :: BSD License
Classifier: Programming Language :: Python
